{"nodes": [{"id": "docs_quality_language_audit_report", "label": "Phase 4A language and comment audit", "file_type": "document", "source_file": "docs/quality/language-audit.md", "source_location": null, "source_url": null, "captured_at": null, "author": null, "contributor": null}, {"id": "docs_quality_language_audit_string_resources", "label": "Spanish es-GT strings.xml resources", "file_type": "concept", "source_file": "docs/quality/language-audit.md", "source_location": null, "source_url": null, "captured_at": null, "author": null, "contributor": null}], "edges": [{"source": "docs_quality_language_audit_report", "target": "docs_quality_language_audit_string_resources", "relation": "references", "confidence": "EXTRACTED", "confidence_score": 1.0, "source_file": "docs/quality/language-audit.md", "source_location": null, "weight": 1.0}], "hyperedges": []}